nuvolasdk/__init__.py
nuvolasdk/__main__.py
nuvolasdk/addondata.py
nuvolasdk/appdata.py
nuvolasdk/checkproject.py
nuvolasdk/convertproject.py
nuvolasdk/createscreenshots.py
nuvolasdk/datadir.py
nuvolasdk/defaults.py
nuvolasdk/genmakefile.py
nuvolasdk/git.py
nuvolasdk/git_version_info.py
nuvolasdk/imaging.py
nuvolasdk/licenses.py
nuvolasdk/newproject.py
nuvolasdk/screenshots.py
nuvolasdk/shkit.py
nuvolasdk/utils.py
nuvolasdk/version.py
nuvolasdk/xmltree.py
nuvolasdk/data/launch_app.sh
nuvolasdk/data/launcher.desktop
nuvolasdk/data/svg-convert.sh
nuvolasdk/data/svg-optimize.sh
nuvolasdk/data/demo/LICENSE
nuvolasdk/data/demo/bootstrap.sh
nuvolasdk/data/demo/integrate.js
nuvolasdk/data/demo/demo/LICENSE
nuvolasdk/data/demo/demo/main.css
nuvolasdk/data/demo/demo/main.html
nuvolasdk/data/demo/demo/main.js
nuvolasdk/data/demo/demo/bootstrap/LICENSE
nuvolasdk/data/demo/demo/bootstrap/css/bootstrap-grid.css
nuvolasdk/data/demo/demo/bootstrap/css/bootstrap-grid.css.map
nuvolasdk/data/demo/demo/bootstrap/css/bootstrap-grid.min.css
nuvolasdk/data/demo/demo/bootstrap/css/bootstrap-grid.min.css.map
nuvolasdk/data/demo/demo/bootstrap/css/bootstrap-reboot.css
nuvolasdk/data/demo/demo/bootstrap/css/bootstrap-reboot.css.map
nuvolasdk/data/demo/demo/bootstrap/css/bootstrap-reboot.min.css
nuvolasdk/data/demo/demo/bootstrap/css/bootstrap-reboot.min.css.map
nuvolasdk/data/demo/demo/bootstrap/css/bootstrap.css
nuvolasdk/data/demo/demo/bootstrap/css/bootstrap.css.map
nuvolasdk/data/demo/demo/bootstrap/css/bootstrap.min.css
nuvolasdk/data/demo/demo/bootstrap/css/bootstrap.min.css.map
nuvolasdk/data/demo/demo/bootstrap/js/bootstrap.bundle.js
nuvolasdk/data/demo/demo/bootstrap/js/bootstrap.bundle.js.map
nuvolasdk/data/demo/demo/bootstrap/js/bootstrap.bundle.min.js
nuvolasdk/data/demo/demo/bootstrap/js/bootstrap.bundle.min.js.map
nuvolasdk/data/demo/demo/bootstrap/js/bootstrap.js
nuvolasdk/data/demo/demo/bootstrap/js/bootstrap.js.map
nuvolasdk/data/demo/demo/bootstrap/js/bootstrap.min.js
nuvolasdk-4.17.0.dist-info/LICENSE
nuvolasdk-4.17.0.dist-info/METADATA
nuvolasdk-4.17.0.dist-info/WHEEL
nuvolasdk-4.17.0.dist-info/top_level.txt
nuvolasdk-4.17.0.dist-info/RECORD
