Metadata-Version: 2.1
Name: nuvolasdk
Version: 4.17.0
Summary: SDK for building Nuvola Apps scripts
Home-page: https://github.com/tiliado/nuvolasdk
Author: Jiří Janoušek
Author-email: janousek.jiri@gmail.com
License: BSD
Keywords: nuvola sdk development
Platform: UNKNOWN
Classifier: Programming Language :: Python :: 3
Classifier: Development Status :: 5 - Production/Stable
Classifier: Intended Audience :: Developers
Classifier: License :: OSI Approved :: BSD License
Classifier: Operating System :: POSIX :: Linux
Classifier: Programming Language :: Python :: 3 :: Only
Requires-Dist: Pillow (>=4.3.0)
